charminder/__init__.py
charminder/cli.py
charminder/encoding_checker.py
charminder/models.py
charminder/reporting.py
charminder/url_utils.py
charminder/bin/check_encoding.py
charminder-0.1.0.dist-info/METADATA
charminder-0.1.0.dist-info/WHEEL
charminder-0.1.0.dist-info/entry_points.txt
charminder-0.1.0.dist-info/licenses/LICENSE
charminder-0.1.0.dist-info/RECORD
