Metadata-Version: 2.4
Name: charminder
Version: 0.1.0
Summary: A character encoding detective for text files and URLs - catch encoding issues before they evolve into problems!
Author-email: Nelson Moore <15333969+nelsonwmoore@users.noreply.github.com>
License-File: LICENSE
Requires-Python: >=3.11
Requires-Dist: charset-normalizer>=3.4.2
Requires-Dist: click>=8.2.1
Requires-Dist: requests>=2.28.0
Provides-Extra: dev
Requires-Dist: mypy>=1.0.0; extra == 'dev'
Requires-Dist: ruff>=0.1.0; extra == 'dev'
Requires-Dist: types-click>=7.1.0; extra == 'dev'
Requires-Dist: types-requests>=2.28.0; extra == 'dev'
Provides-Extra: test
Requires-Dist: pytest-cov>=4.0.0; extra == 'test'
Requires-Dist: pytest>=7.0.0; extra == 'test'
Requires-Dist: responses>=0.24.0; extra == 'test'
